vedro_spec_compare/__init__.py
vedro_spec_compare/changes.py
vedro_spec_compare/command.py
vedro_spec_compare/coverage.py
vedro_spec_compare/differ.py
vedro_spec_compare/discrepancy.py
vedro_spec_compare/generator.py
vedro_spec_compare/models.py
vedro_spec_compare/parser.py
vedro_spec_compare/templates/changes.html.j2
vedro_spec_compare/templates/coverage.html.j2
vedro_spec_compare/templates/discrepancy.html.j2
vedro_spec_compare-0.9.0.dist-info/LICENSE
vedro_spec_compare-0.9.0.dist-info/METADATA
vedro_spec_compare-0.9.0.dist-info/WHEEL
vedro_spec_compare-0.9.0.dist-info/entry_points.txt
vedro_spec_compare-0.9.0.dist-info/top_level.txt
vedro_spec_compare-0.9.0.dist-info/RECORD
