Metadata-Version: 2.2
Name: vedro-spec-compare
Version: 0.9.0
Summary: OpenAPI spec compare
Home-page: https://github.com/kvs8/vedro-spec-compare
Author: Konstantin Shefer
Author-email: kostya.shefer.999@gmail.com
License: Apache-2.0
Classifier: License :: OSI Approved :: Apache Software License
Classifier: Programming Language :: Python :: 3.10
Classifier: Programming Language :: Python :: 3.11
Classifier: Programming Language :: Python :: 3.12
Requires-Python: >=3.8
License-File: LICENSE
Requires-Dist: jinja2<4.0.0,>=3.1.4
Requires-Dist: schemax<3.0.0,>=2.0.2
Requires-Dist: PyYAML<7.0.0,>=6.0.2
Requires-Dist: requests<3.0.0,>=2.32.3
Dynamic: author
Dynamic: author-email
Dynamic: classifier
Dynamic: description
Dynamic: description-content-type
Dynamic: home-page
Dynamic: license
Dynamic: requires-dist
Dynamic: requires-python
Dynamic: summary
